{
  "$schema": "https://turbo.build/schema.json",
  "ui": "stream",
  "tasks": {
    "build": {
      "dependsOn": [
        "^build"
      ],
      "outputs": [
        "dist/**",
        "dist-esm/**",
        "dist-test/**",
        "types/**"
      ]
    },
    "check-format": {
      "cache": false
    },
    "clean": {
      "cache": false
    },
    "format": {
      "cache": false
    },
    "lint": {
      "cache": false
    },
    "lint:fix": {
      "cache": false
    },
    "pack": {
      "dependsOn": [
        "build"
      ],
      "cache": false
    },
    "test": {
      "dependsOn": [
        "build"
      ]
    },
    "dev": {
      "cache": true,
      "persistent": true
    }
  }
}
